{
  "status": "completed",
  "initial_cash": 100000,
  "final_value": 99900.62361366274,
  "total_return": -0.09937638633725873,
  "symbols": [
    "AAPL",
    "MSFT",
    "GOOGL",
    "TSLA",
    "NVDA"
  ],
  "start_date": "2025-06-03",
  "end_date": "2025-09-01",
  "total_trades": 0,
  "winning_trades": 0,
  "losing_trades": 0,
  "win_rate": 0,
  "avg_profit": 0,
  "avg_loss": 0,
  "sharpe_ratio": 0.39910148892728853,
  "total_decisions": 310,
  "buy_signals": 158,
  "sell_signals": 0,
  "hold_signals": 152,
  "symbol_pnl": {},
  "grand_total_pnl": 0
}